django_spectre_css/__init__.py
django_spectre_css/static/css/lib/spectre-exp.css
django_spectre_css/static/css/lib/spectre-icons.css
django_spectre_css/static/css/lib/spectre.css
django_spectre_css/templates/spectre-css/form-header.html
django_spectre_css/templates/spectre-css/form.html
django_spectre_css/templates/spectre-css/generic-field.html
django_spectre_css/templates/spectre-css/multi-field-input-group.html
django_spectre_css/templates/spectre-css/render-form-checkbox.html
django_spectre_css/templates/spectre-css/render-form-field.html
django_spectre_css/templates/spectre-css/render-form-radio.html
django_spectre_css/templates/spectre-css/render-form-select.html
django_spectre_css/templates/spectre-css/render-form-textarea.html
django_spectre_css/templates/spectre-css/render-multi-field-part.html
django_spectre_css/templates/spectre-css/render-multi-field.html
django_spectre_css/templates/spectre-css/render_errors.html
django_spectre_css/templatetags/__init__.py
django_spectre_css/templatetags/spectre_css.py
django_spectre_css/templatetags/widget_tweaks_extras.py
django_spectre_css-0.3.dev2.dist-info/METADATA
django_spectre_css-0.3.dev2.dist-info/WHEEL
django_spectre_css-0.3.dev2.dist-info/licenses/LICENSE
django_spectre_css-0.3.dev2.dist-info/RECORD
